prompt_decorators/__init__.py
prompt_decorators/__main__.py
prompt_decorators/config.py
prompt_decorators/core/__init__.py
prompt_decorators/core/base.py
prompt_decorators/core/dynamic_decorator.py
prompt_decorators/core/exceptions.py
prompt_decorators/core/model_specific.py
prompt_decorators/core/parser.py
prompt_decorators/core/registry.py
prompt_decorators/core/request.py
prompt_decorators/core/validation.py
prompt_decorators/dynamic_decorators_module.py
prompt_decorators/integrations/__init__.py
prompt_decorators/integrations/mcp/__init__.py
prompt_decorators/integrations/mcp/__main__.py
prompt_decorators/integrations/mcp/claude_desktop.py
prompt_decorators/integrations/mcp/install_claude_desktop.py
prompt_decorators/integrations/mcp/server.py
prompt_decorators/py.typed
prompt_decorators/registry/core/meta/build-on.json
prompt_decorators/registry/core/meta/chain.json
prompt_decorators/registry/core/meta/compatibility.json
prompt_decorators/registry/core/meta/conditional.json
prompt_decorators/registry/core/meta/context.json
prompt_decorators/registry/core/meta/custom.json
prompt_decorators/registry/core/meta/extension.json
prompt_decorators/registry/core/meta/override.json
prompt_decorators/registry/core/meta/priority.json
prompt_decorators/registry/core/meta/refine.json
prompt_decorators/registry/core/minimal/output-format.json
prompt_decorators/registry/core/minimal/reasoning.json
prompt_decorators/registry/core/minimal/step-by-step.json
prompt_decorators/registry/core/minimal/tone.json
prompt_decorators/registry/core/minimal/version.json
prompt_decorators/registry/core/reasoning/abductive.json
prompt_decorators/registry/core/reasoning/analogical.json
prompt_decorators/registry/core/reasoning/blind-spots.json
prompt_decorators/registry/core/reasoning/contrarian.json
prompt_decorators/registry/core/reasoning/debate.json
prompt_decorators/registry/core/reasoning/deductive.json
prompt_decorators/registry/core/reasoning/first-principles.json
prompt_decorators-0.9.0.dist-info/LICENSE
prompt_decorators-0.9.0.dist-info/METADATA
prompt_decorators-0.9.0.dist-info/WHEEL
prompt_decorators-0.9.0.dist-info/RECORD
