Metadata-Version: 2.3
Name: prompt-decorators
Version: 0.9.0
Summary: A framework for defining, managing, and applying prompt decorators to enhance interactions with LLMs
License: Apache-2.0
Author: Daniel Bentes
Author-email: promptdecorators@synapti.ai
Requires-Python: >=3.11,<4.0
Classifier: Development Status :: 3 - Alpha
Classifier: Intended Audience :: Developers
Classifier: License :: OSI Approved :: Apache Software License
Classifier: Programming Language :: Python :: 3
Classifier: Programming Language :: Python :: 3.11
Classifier: Programming Language :: Python :: 3.12
Classifier: Programming Language :: Python :: 3.13
Requires-Dist: importlib-metadata (>=6.0.0,<7.0.0)
Requires-Dist: jsonschema (>=4.0.0,<5.0.0)
Requires-Dist: markdown (>=3.7,<4.0)
Requires-Dist: pydantic (>=2.0.0,<3.0.0)
Project-URL: Documentation, https://synaptiai.github.io/prompt-decorators/
Project-URL: Issue Tracker, https://github.com/synaptiai/prompt-decorators/issues
Project-URL: Source, https://github.com/synaptiai/prompt-decorators
